{
  "postType": "infographic",
  "title": "Smart Investment Secrets TikTok Won't Tell You",
  "description": "Stop wasting money! Learn smart investment strategies that actually work. Save more, spend less, build wealth faster. #SmartInvesting #PersonalFinance #WealthBuilding",
  "topic": "smart investment",
  "slideCount": 6,
  "slides": [
    {
      "file": "01.jpg",
      "slideRole": "hook",
      "imageTitle": "MONEY MISTAKES",
      "topic": "common money mistakes",
      "topSection": "Show 3 wasteful spending icons (coffee shop, luxury clothes, takeout) with red X center, caption: 'Throwing cash away daily'",
      "bottomSection": "Show 3 growing investment icons (stock graph, real estate, gold bars) with green check center, caption: 'Wealth compounding over time'",
      "index": 1
    },
    {
      "file": "02.jpg",
      "slideRole": "build",
      "imageTitle": "COMPOUND POWER",
      "topic": "compound interest growth",
      "topSection": "Show small amount ($100 bill) with red X, 3 year timeline with decreasing value, caption: 'Cash loses purchasing power'",
      "bottomSection": "Show same amount growing through 10 years with green check, upward arrow and dollar signs, caption: 'Investments multiply over time'",
      "index": 2
    },
    {
      "file": "03.jpg",
      "slideRole": "build",
      "imageTitle": "RISK REALITY",
      "topic": "risk versus reward",
      "topSection": "Show lottery ticket, crypto crash, get rich quick schemes with red X, caption: 'High risk, usually losses'",
      "bottomSection": "Show steady index fund, dividend stocks, bonds with green check, caption: 'Consistent returns win long-term'",
      "index": 3
    },
    {
      "file": "04.jpg",
      "slideRole": "build",
      "imageTitle": "INFLATION KILLER",
      "topic": "inflation impact on cash",
      "topSection": "Show cash stack with red X, price tags rising, '100% cash losing value', caption: 'Cash erodes with inflation'",
      "bottomSection": "Show diversified portfolio with green check, steady growth arrows, 'Balanced assets beat inflation', caption: 'Investments preserve value'",
      "index": 4
    },
    {
      "file": "05.jpg",
      "slideRole": "build",
      "imageTitle": "DIVERSIFICATION",
      "topic": "portfolio diversification",
      "topSection": "Show single stock basket with red X, cracking open, 'All eggs in one basket', caption: 'Concentrated risk dangerous'",
      "bottomSection": "Show pie chart portfolio with green check, multiple slices, 'Spread across sectors', caption: 'Diversified = less risk'",
      "index": 5
    },
    {
      "file": "06.jpg",
      "slideRole": "build",
      "imageTitle": "FEE DAMAGE",
      "topic": "investment fees impact",
      "topSection": "Show expensive advisor with red X, fee calculator, '2% fees eat returns', caption: 'High fees destroy gains'",
      "bottomSection": "Show low cost index fund with green check, fee calculator at 0.1%, 'Minimal fees maximize growth', caption: 'Low cost = more profit'",
      "index": 6
    }
  ],
  "files": [
    "01.jpg",
    "02.jpg",
    "03.jpg",
    "04.jpg",
    "05.jpg",
    "06.jpg"
  ],
  "imageGen": {
    "model": "x-ai/grok-imagine-image-quality",
    "aspectRatio": "1:1",
    "width": 1080,
    "height": 1080,
    "slides": [
      {
        "file": "01.jpg",
        "imageTitle": "MONEY MISTAKES",
        "topic": "common money mistakes",
        "promptFile": "_prompts/01.txt"
      },
      {
        "file": "02.jpg",
        "imageTitle": "COMPOUND POWER",
        "topic": "compound interest growth",
        "promptFile": "_prompts/02.txt"
      },
      {
        "file": "03.jpg",
        "imageTitle": "RISK REALITY",
        "topic": "risk versus reward",
        "promptFile": "_prompts/03.txt"
      },
      {
        "file": "04.jpg",
        "imageTitle": "INFLATION KILLER",
        "topic": "inflation impact on cash",
        "promptFile": "_prompts/04.txt"
      },
      {
        "file": "05.jpg",
        "imageTitle": "DIVERSIFICATION",
        "topic": "portfolio diversification",
        "promptFile": "_prompts/05.txt"
      },
      {
        "file": "06.jpg",
        "imageTitle": "FEE DAMAGE",
        "topic": "investment fees impact",
        "promptFile": "_prompts/06.txt"
      }
    ]
  },
  "createdAt": "2026-05-29T16:08:02.786Z"
}
